alsangue/__init__.py
alsangue/example/.gitignore
alsangue/example/build/index.html
alsangue/example/build/sitemap.xml
alsangue/example/build/archive/you.html
alsangue/example/build/articles/example_page.html
alsangue/example/build/authors/you.html
alsangue/example/build/it/index.html
alsangue/example/build/it/archive/you.html
alsangue/example/build/it/articles/example_page.html
alsangue/example/build/it/authors/you.html
alsangue/example/content/config
alsangue/example/content/articles/example_page
alsangue/example/content/authors/you
alsangue/example/content/templates/archive.html
alsangue/example/content/templates/article.html
alsangue/example/content/templates/author.html
alsangue/locales/en_US.UTF-8
alsangue/locales/it_IT.UTF-8
alsangue-0.2.dist-info/LICENSE
alsangue-0.2.dist-info/METADATA
alsangue-0.2.dist-info/WHEEL
alsangue-0.2.dist-info/entry_points.txt
alsangue-0.2.dist-info/top_level.txt
alsangue-0.2.dist-info/RECORD
