Metadata-Version: 2.1
Name: alsangue
Version: 0.2
Summary: naive static website builder
Home-page: https://github.com/tallero/alsangue
Author: Pellegrino Prevete
Author-email: pellegrinoprevete@gmail.com
License: UNKNOWN
Platform: UNKNOWN
Classifier: Programming Language :: Python :: 3
Classifier: License :: OSI Approved :: GNU General Public License v3 or later (GPLv3+)
Classifier: Operating System :: Unix
Requires-Dist: setproctitle
Requires-Dist: beautifulsoup4
